{
    "aws1": {
        "room_2": {},
        "room_3": {},
        "room_4": {},
        "room_5": {},
        "room_6": {},
        "room_7": {
            "(175, 210)": {},
            "(176, 159)": {},
            "(85, 67)": {},
            "(85, 139)": {},
            "(147, 67)": {},
            "(147, 24)": {},
            "(85, 159)": {},
            "(45, 161)": {},
            "(74, 160)": {},
            "(102, 24)": {},
            "(102, 67)": {},
            "(168, 159)": {},
            "(168, 139)": {},
            "(84, 160)": {},
            "(168, 67)": {},
            "(75, 210)": {},
            "(204, 160)": {},
            "room_19_(75, 210)_bridge": {},
            "room_20_(175, 210)_bridge": {},
            "(140, 28)": {},
            "(140, 24)": {},
            "aws2_room_7_(140, 28)_bridge": {}
        },
        "room_8": {},
        "room_9": {},
        "room_10": {},
        "room_11": {},
        "room_12": {},
        "room_13": {},
        "room_14": {},
        "room_15": {
            "(19, 185)": {},
            "(28, 185)": {},
            "room_17_(28, 185)_bridge": {}
        },
        "room_16": {},
        "room_17": {
            "(31, 188)": {},
            "(37, 222)": {},
            "(44, 301)": {},
            "(44, 302)": {},
            "(30, 188)": {},
            "(28, 185)": {},
            "(57, 301)": {},
            "(58, 301)": {},
            "(44, 222)": {},
            "room_15_(28, 185)_bridge": {},
            "room_19_(58, 301)_bridge": {}
        },
        "room_18": {},
        "room_19": {
            "(74, 459)": {},
            "(74, 537)": {},
            "(75, 210)": {},
            "(74, 217)": {},
            "(90, 454)": {},
            "(74, 454)": {},
            "(74, 295)": {},
            "(74, 301)": {},
            "(58, 301)": {},
            "(59, 459)": {},
            "(98, 528)": {},
            "(98, 536)": {},
            "(74, 355)": {},
            "(74, 441)": {},
            "(90, 295)": {},
            "(50, 529)": {},
            "(50, 536)": {},
            "(97, 537)": {},
            "(58, 441)": {},
            "(90, 355)": {},
            "(74, 552)": {},
            "(51, 537)": {},
            "room_7_(75, 210)_bridge": {},
            "room_20_(90, 295)_bridge": {},
            "room_20_(90, 355)_bridge": {},
            "room_20_(90, 454)_bridge": {},
            "room_17_(58, 301)_bridge": {},
            "room_32_(58, 441)_bridge": {}
        },
        "room_20": {
            "(191, 441)": {},
            "(174, 441)": {},
            "(178, 470)": {},
            "(178, 463)": {},
            "(191, 301)": {},
            "(174, 301)": {},
            "(174, 355)": {},
            "(174, 217)": {},
            "(174, 295)": {},
            "(90, 454)": {},
            "(174, 454)": {},
            "(177, 462)": {},
            "(90, 295)": {},
            "(174, 462)": {},
            "(90, 355)": {},
            "(175, 210)": {},
            "room_7_(175, 210)_bridge": {},
            "room_19_(90, 295)_bridge": {},
            "room_19_(90, 355)_bridge": {},
            "room_19_(90, 454)_bridge": {},
            "room_21_(191, 301)_bridge": {},
            "room_33_(191, 441)_bridge": {},
            "room_37_(178, 470)_bridge": {}
        },
        "room_21": {
            "(191, 301)": {},
            "(192, 301)": {},
            "(204, 301)": {},
            "(204, 302)": {},
            "(204, 222)": {},
            "room_20_(191, 301)_bridge": {}
        },
        "room_22": {},
        "room_23": {},
        "room_24": {},
        "room_25": {},
        "room_26": {},
        "room_27": {},
        "room_28": {},
        "room_29": {},
        "room_30": {},
        "room_31": {
            "(35, 339)": {},
            "(35, 351)": {},
            "room_32_(35, 351)_bridge": {}
        },
        "room_32": {
            "(52, 362)": {},
            "(35, 362)": {},
            "(57, 441)": {},
            "(52, 441)": {},
            "(31, 442)": {},
            "(52, 442)": {},
            "(58, 441)": {},
            "(31, 362)": {},
            "(35, 351)": {},
            "room_31_(35, 351)_bridge": {},
            "room_19_(58, 441)_bridge": {}
        },
        "room_33": {
            "(212, 362)": {},
            "(206, 362)": {},
            "(214, 351)": {},
            "(192, 441)": {},
            "(206, 441)": {},
            "(206, 442)": {},
            "(191, 441)": {},
            "room_20_(191, 441)_bridge": {}
        },
        "room_34": {},
        "room_35": {},
        "room_36": {},
        "room_37": {
            "(154, 484)": {},
            "(178, 484)": {},
            "(211, 484)": {},
            "(97, 484)": {},
            "(154, 511)": {},
            "(178, 470)": {},
            "room_20_(178, 470)_bridge": {}
        },
        "room_38": {},
        "room_39": {},
        "room_40": {
            "(239, 506)": {},
            "(239, 516)": {}
        },
        "room_41": {},
        "room_42": {},
        "room_43": {},
        "room_44": {},
        "room_45": {},
        "aws2_room_7_bridge": {}
    },
    "aws2": {
        "room_2": {},
        "room_3": {},
        "room_4": {},
        "room_5": {},
        "room_6": {},
        "room_7": {
            "(204, 160)": {},
            "(176, 159)": {},
            "(85, 67)": {},
            "(85, 139)": {},
            "(169, 159)": {},
            "(168, 158)": {},
            "(75, 210)": {},
            "(74, 160)": {},
            "(85, 160)": {},
            "(102, 24)": {},
            "(102, 67)": {},
            "(168, 139)": {},
            "(168, 67)": {},
            "(45, 161)": {},
            "(147, 24)": {},
            "(175, 210)": {},
            "(147, 67)": {},
            "room_19_(75, 210)_bridge": {},
            "room_20_(175, 210)_bridge": {},
            "(140, 28)": {},
            "(140, 24)": {},
            "aws1_room_7_(140, 28)_bridge": {}
        },
        "room_8": {},
        "room_9": {},
        "room_10": {},
        "room_11": {},
        "room_12": {},
        "room_13": {},
        "room_14": {},
        "room_15": {
            "(19, 185)": {},
            "(28, 185)": {},
            "room_17_(28, 185)_bridge": {}
        },
        "room_16": {},
        "room_17": {
            "(31, 188)": {},
            "(37, 222)": {},
            "(44, 301)": {},
            "(44, 302)": {},
            "(30, 188)": {},
            "(28, 185)": {},
            "(57, 301)": {},
            "(58, 301)": {},
            "(44, 222)": {},
            "room_15_(28, 185)_bridge": {},
            "room_19_(58, 301)_bridge": {}
        },
        "room_18": {},
        "room_19": {
            "(74, 459)": {},
            "(74, 537)": {},
            "(75, 210)": {},
            "(74, 217)": {},
            "(90, 454)": {},
            "(74, 454)": {},
            "(74, 295)": {},
            "(74, 301)": {},
            "(58, 301)": {},
            "(59, 459)": {},
            "(98, 528)": {},
            "(98, 536)": {},
            "(74, 355)": {},
            "(74, 441)": {},
            "(90, 295)": {},
            "(50, 529)": {},
            "(50, 536)": {},
            "(97, 537)": {},
            "(58, 441)": {},
            "(90, 355)": {},
            "(74, 552)": {},
            "(51, 537)": {},
            "room_7_(75, 210)_bridge": {},
            "room_20_(90, 295)_bridge": {},
            "room_20_(90, 355)_bridge": {},
            "room_20_(90, 454)_bridge": {},
            "room_17_(58, 301)_bridge": {},
            "room_32_(58, 441)_bridge": {}
        },
        "room_20": {
            "(191, 441)": {},
            "(174, 441)": {},
            "(178, 470)": {},
            "(178, 463)": {},
            "(191, 301)": {},
            "(174, 301)": {},
            "(174, 355)": {},
            "(174, 217)": {},
            "(174, 295)": {},
            "(90, 454)": {},
            "(174, 454)": {},
            "(177, 462)": {},
            "(90, 295)": {},
            "(174, 462)": {},
            "(90, 355)": {},
            "(175, 210)": {},
            "room_7_(175, 210)_bridge": {},
            "room_19_(90, 295)_bridge": {},
            "room_19_(90, 355)_bridge": {},
            "room_19_(90, 454)_bridge": {},
            "room_21_(191, 301)_bridge": {},
            "room_33_(191, 441)_bridge": {},
            "room_37_(178, 470)_bridge": {}
        },
        "room_21": {
            "(191, 301)": {},
            "(192, 301)": {},
            "(204, 301)": {},
            "(204, 302)": {},
            "(204, 222)": {},
            "room_20_(191, 301)_bridge": {}
        },
        "room_22": {},
        "room_23": {},
        "room_24": {},
        "room_25": {},
        "room_26": {},
        "room_27": {},
        "room_28": {},
        "room_29": {},
        "room_30": {},
        "room_31": {
            "(35, 339)": {},
            "(35, 351)": {},
            "room_32_(35, 351)_bridge": {}
        },
        "room_32": {
            "(52, 362)": {},
            "(35, 362)": {},
            "(57, 441)": {},
            "(52, 441)": {},
            "(31, 442)": {},
            "(52, 442)": {},
            "(58, 441)": {},
            "(31, 362)": {},
            "(35, 351)": {},
            "room_31_(35, 351)_bridge": {},
            "room_19_(58, 441)_bridge": {}
        },
        "room_33": {
            "(212, 362)": {},
            "(206, 362)": {},
            "(214, 351)": {},
            "(192, 441)": {},
            "(206, 441)": {},
            "(206, 442)": {},
            "(191, 441)": {},
            "room_20_(191, 441)_bridge": {}
        },
        "room_34": {},
        "room_35": {},
        "room_36": {},
        "room_37": {
            "(154, 484)": {},
            "(178, 484)": {},
            "(211, 484)": {},
            "(97, 484)": {},
            "(154, 511)": {},
            "(178, 470)": {},
            "room_20_(178, 470)_bridge": {}
        },
        "room_38": {},
        "room_39": {},
        "room_40": {
            "(239, 506)": {},
            "(239, 516)": {}
        },
        "room_41": {},
        "room_42": {},
        "room_43": {},
        "room_44": {},
        "room_45": {},
        "aws1_room_7_bridge": {}
    }
}